NPyUtils/LstUtils.py
NPyUtils/NCaptcha.py
NPyUtils/NPyUtils.py
NPyUtils/__init__.py
npyutils-0.0.2.dist-info/licenses/LICENSE
npyutils-0.0.2.dist-info/METADATA
npyutils-0.0.2.dist-info/WHEEL
npyutils-0.0.2.dist-info/top_level.txt
npyutils-0.0.2.dist-info/RECORD
