Metadata-Version: 2.4
Name: NPyUtils
Version: 0.0.2
Summary: A simple Python Utils Pkg
Author-email: namo <none@none.com>
License: MIT License
Keywords: utility,python
Requires-Python: >=3.7
License-File: LICENSE
Dynamic: license-file
